{
  "title": "ุฏููู ุงูุฅุตุงุจุงุช ุงูุฑูุงุถูุฉ ูููุจุชุฏุฆูู ูุงููุชูุณุทูู ๐ช",
  "subtitle": "ุจุต ูุง ุจุทูุ ุงูุฌูู ููุงู ุฑุงุฆุน ุจุณ ูุงุฒู ูุญุงูุธ ุนูู ููุณูุง! ๐ฅ",
  "introduction": "ููุง ูุชูุงูู ูู ุญุงุฌุฉ ุนู ุงูุฅุตุงุจุงุช ุงููู ูููู ุชุญุตู ูู ุงูุฌูู ูุฅุฒุงู ุชุชุฌูุจูุง ูุชุชุนุงูู ูุนุงูุง ูู ุญุตูุช. ุฎูู ุจุงููุ ุงูููุงูุฉ ุฃุญุณู ูู ุงูุนูุงุฌ! โ๏ธ",
  
  "general_tips": {
    "title": "ูุตุงูุญ ุนุงูุฉ ูููุฉ ุฌุฏุงู ๐ฏ",
    "tips": [
      "๐ฅ ุณุฎู ูููุณ ูุจู ุฃู ุชูุฑูู - 10-15 ุฏูููุฉ ุนูู ุงูุฃูู",
      "๐ง ุงุดุฑุจ ููุฉ ูุชูุฑ ุนุดุงู ุงูุนุถูุงุช ุชูุถู ูุฑุทุจุฉ",
      "โ๏ธ ุฒูุฏ ุงูุฃูุฒุงู ุชุฏุฑูุฌู - ูุด ุนูุจ ุชุจุฏุฃ ุฎููู",
      "๐ฏ ุฑูุฒ ุนูู ุงูุญุฑูุฉ ุงูุตุญ ุฃูู ูู ุงููุฒู ุงููุจูุฑ",
      "๐ด ูุงู ูููุณ ุนุดุงู ุงูุนุถูุงุช ุชุณุชุดูู",
      "๐ ูู ุฃูู ุตุญู ูุณุงุนุฏ ุนูู ุงูุงุณุชุดูุงุก"
    ]
  },

  "injuries": [
    {
      "name_arabic": "ุดุฏ ุนุถูุฉ ุงูุถูุฑ",
      "name_english": "Lower Back Strain",
      "emoji": "๐ฅ",
      "affected_area": "ุฃุณูู ุงูุถูุฑ (ุงูููุฑุงุช ุงููุทููุฉ)",
      "causes": [
        "ุฑูุน ุฃูุฒุงู ุชูููุฉ ุจุธูุฑ ูุญูู ๐",
        "ุนูู ุฏูุฏูููุช ุฃู ุณููุงุช ุจูุถุนูุฉ ุบูุท",
        "ุนุฏู ุชุณุฎูู ุงูุนุถูุงุช ูุจู ุงูุชูุฑูู",
        "ุถุนู ุนุถูุงุช ุงูุจุทู (ุงูููุฑ)",
        "ุงูุฌููุณ ูุชุฑุงุช ุทูููุฉ ูุจู ุงูุชูุฑูู"
      ],
      "symptoms": [
        "ุฃูู ุญุงุฏ ูู ุฃุณูู ุงูุถูุฑ ๐ฃ",
        "ุชูุจุณ ูุตุนูุจุฉ ูู ุงูุญุฑูุฉ",
        "ุฃูู ุจูุฒูุฏ ููุง ุชูุญูู ุฃู ุชููู",
        "ุฃุญูุงูุงู ุฃูู ููุฒู ููุฑุฌู",
        "ุชุดูุฌ ูู ุนุถูุงุช ุงูุถูุฑ"
      ],
      "first_aid": [
        "๐ ููู ุงูุชูุฑูู ููุฑุงู",
        "๐ง ุญุท ุชูุฌ ููุฏุฉ 15-20 ุฏูููุฉ ูู ุณุงุนุชูู",
        "๐๏ธ ูุงู ุนูู ุถูุฑู ูุน ุฑูุน ุงูุฑุฌููู",
        "๐ ูููู ุชุงุฎุฏ ูุณูู ุจุณูุท (ุจุฑูููู)",
        "๐ซ ูุชุญุงููุด ุชููู ุชูุฑูู ุฃู ุชุดูู ุญุงุฌุฉ ุชูููุฉ"
      ],
      "when_to_see_doctor": [
        "๐จ ุงูุฃูู ุดุฏูุฏ ุฌุฏุงู ููุด ุจููุฏุฃ",
        "๐ฆต ุงูุฃูู ูุงุฒู ููุฑุฌู ูุน ุชูููู",
        "โฐ ุงูุฃูู ูุณุชูุฑ ุฃูุชุฑ ูู 3 ุฃูุงู",
        "๐ถโโ๏ธ ูุด ูุงุฏุฑ ุชูุดู ุฃู ุชููู ูู ุงูุณุฑูุฑ",
        "๐ฉ ูุดุงูู ูู ุงูุชุญูู ูู ุงูุจูู ุฃู ุงูุจุฑุงุฒ"
      ],
      "recovery_plan": [
        "๐ถโโ๏ธ ุงุจุฏุฃ ุจูุดู ุฎููู ุจุนุฏ ูุง ุงูุฃูู ููุฏุฃ",
        "๐งโโ๏ธ ุชูุงุฑูู ุฅุทุงูุฉ ุฎูููุฉ ููุถูุฑ",
        "๐ช ููู ุนุถูุงุช ุงูุจุทู ูุงูุถูุฑ ุชุฏุฑูุฌูุงู",
        "๐๏ธโโ๏ธ ุงุฑุฌุน ููุฃูุฒุงู ุจุญุฐุฑ ูุงุจุฏุฃ ุฎููู",
        "๐ฏ ุฑูุฒ ุนูู ุชุตุญูุญ ุงููุถุนูุฉ"
      ],
      "prevention": [
        "๐ฅ ุณุฎู ูููุณ ูุจู ุฃู ุชูุฑูู ุถูุฑ",
        "๐ ุญุงูุธ ุนูู ุงูุญูุงุก ุทุจูุนู ููุถูุฑ",
        "๐ช ููู ุนุถูุงุช ุงูุจุทู ูุงูููุฑ",
        "โ๏ธ ุงุจุฏุฃ ุจุฃูุฒุงู ุฎูููุฉ ูุฒูุฏ ุชุฏุฑูุฌู",
        "๐ ุงุชุนูู ุงูุญุฑูุฉ ุงูุตุญ ูุจู ูุง ุชุฒูุฏ ุงููุฒู"
      ]
    },
    
    {
      "name_arabic": "ุงูุชูุงุจ ุฃูุชุงุฑ ุงูุฑูุจุฉ",
      "name_english": "Knee Tendinitis",
      "emoji": "๐ฆต",
      "affected_area": "ุงูุฑูุจุฉ (ุงูุฃูุชุงุฑ ุญูุงููู ุงูุตุงุจููุฉ)",
      "causes": [
        "ุชูุงุฑูู ููุฒ ูุชูุฑุฉ (ุฌุงูุจููุฌ ุฌุงูุณุ ุจููุณ ุฌุงูุจ) ๐ฆ",
        "ุฒูุงุฏุฉ ุดุฏุฉ ุงูุชูุฑูู ุจุณุฑุนุฉ",
        "ุนูู ุณููุงุช ุฃู ูุงูุฌุฒ ุจูุถุนูุฉ ุบูุท",
        "ุถุนู ุนุถูุงุช ุงููุฎุฐ ุงูุฃูุงููุฉ ูุงูุฎูููุฉ",
        "ุนุฏู ุฅุทุงูุฉ ุงูุนุถูุงุช ุจุนุฏ ุงูุชูุฑูู"
      ],
      "symptoms": [
        "ุฃูู ุญูู ุงูุตุงุจููุฉ ุฎุงุตุฉ ุชุญุชูุง ๐",
        "ุฃูู ุจูุฒูุฏ ูุน ุตุนูุฏ ุงูุณูู",
        "ุชูุจุณ ูู ุงูุฑูุจุฉ ุงูุตุจุญ",
        "ุฃูู ุจุนุฏ ุงูุฌููุณ ูุชุฑุฉ ุทูููุฉ",
        "ุฃุญูุงูุงู ุชูุฑู ุฎููู"
      ],
      "first_aid": [
        "๐ ููู ุงูุชูุงุฑูู ุงููู ูููุง ููุฒ ุฃู ุถุบุท ุนูู ุงูุฑูุจุฉ",
        "๐ง ุชูุฌ ููุฏุฉ 15 ุฏูููุฉุ 3-4 ูุฑุงุช ูู ุงูููู",
        "๐ฆต ุงุฑูุน ุงูุฑุฌู ูุงูุช ูุงูู",
        "๐ ูุณูู ุจุณูุท ูู ุงูุฃูู ุดุฏูุฏ",
        "๐ซ ุชุฌูุจ ุงูุฌุฑู ุฃู ุงูููุฒ"
      ],
      "when_to_see_doctor": [
        "๐จ ุงูุฃูู ุดุฏูุฏ ููุด ุจูุชุญุณู ุจุนุฏ ุฃุณุจูุน",
        "๐ ุชูุฑู ูุงุถุญ ูู ุงูุฑูุจุฉ",
        "๐ ูุด ูุงุฏุฑ ุชุซูู ุฃู ุชูุฑุฏ ุงูุฑูุจุฉ",
        "๐ถโโ๏ธ ุตุนูุจุฉ ูู ุงููุดู",
        "๐ก๏ธ ุณุฎููุฉ ุฃู ุงุญูุฑุงุฑ ูู ุงูุฑูุจุฉ"
      ],
      "recovery_plan": [
        "๐โโ๏ธ ุชูุงุฑูู ูุงุฆูุฉ ุฃู ุนุฌูุฉ ุซุงุจุชุฉ",
        "๐งโโ๏ธ ุฅุทุงูุฉ ุนุถูุงุช ุงููุฎุฐ ูุงูุณูุงูุฉ",
        "๐ช ุชูููุฉ ุนุถูุงุช ุงููุฎุฐ ุงูุฃูุงููุฉ (ููุงุฏุฒ)",
        "๐ฏ ุชูุงุฑูู ุชูุงุฒู ูุซุจุงุช",
        "๐๏ธโโ๏ธ ุงุฑุฌุน ููุชูุงุฑูู ุชุฏุฑูุฌูุงู"
      ],
      "prevention": [
        "๐ฅ ุณุฎู ูููุณ ูุจู ุชูุงุฑูู ุงูุฑุฌู",
        "๐ ุชุฃูุฏ ูู ูุถุนูุฉ ุงูุณููุงุช ุงูุตุญ",
        "๐ช ููู ุนุถูุงุช ุงููุฎุฐ ุจุงูุชุธุงู",
        "๐งโโ๏ธ ุงุนูู ุฅุทุงูุฉ ุจุนุฏ ูู ุชูุฑูู",
        "๐ ุงูุจุณ ุญุฐุงุก ุฑูุงุถู ููุงุณุจ"
      ]
    },

    {
      "name_arabic": "ุงูุญุดุงุฑ ุงููุชู",
      "name_english": "Shoulder Impingement",
      "emoji": "๐คทโโ๏ธ",
      "affected_area": "ุงููุชู (ุฎุงุตุฉ ุงูุฌุฒุก ุงูุนููู)",
      "causes": [
        "ุชูุงุฑูู ูุชู ูุชูุฑุฉ ุจุฏูู ุฑุงุญุฉ ๐๏ธโโ๏ธ",
        "ุฑูุน ุงูุฃูุฒุงู ููู ุงูุฑุงุณ ุจูุถุนูุฉ ุบูุท",
        "ุถุนู ุนุถูุงุช ุงููุชู ุงูุฎูููุฉ",
        "ุชูุฑุงุฑ ุญุฑูุงุช ุงููุชู ุจุดูู ููุฑุท",
        "ุนุฏู ุชูุงุฒู ุจูู ุนุถูุงุช ุงููุชู ุงูุฃูุงููุฉ ูุงูุฎูููุฉ"
      ],
      "symptoms": [
        "ุฃูู ูู ุงููุชู ุฎุงุตุฉ ููุง ุชุฑูุน ุฅูุฏู ููู ๐ฃ",
        "ุฃูู ุจุงูููู ููุง ุชูุงู ุนูู ุงููุชู ุงููุตุงุจ",
        "ุถุนู ูู ููุฉ ุงููุชู",
        "ุตูุช ุทูุทูุฉ ุฃู ุงุญุชูุงู",
        "ุฃูู ุจููุชุฏ ููุฐุฑุงุน"
      ],
      "first_aid": [
        "๐ ุชุฌูุจ ุฑูุน ุงูุฃูุฒุงู ููู ูุณุชูู ุงููุชู",
        "๐ง ุชูุฌ ููุฏุฉ 15 ุฏูููุฉ ุนุฏุฉ ูุฑุงุช",
        "๐ ูุณูู ุงูุชูุงุจ (ุฅูุจูุจุฑูููู)",
        "๐คฒ ุญุฑู ุงููุชู ุจุฑูู ูู ุฏูุงุฆุฑ ุตุบูุฑุฉ",
        "๐ซ ูุชูุงูุด ุนูู ุงููุชู ุงููุตุงุจ"
      ],
      "when_to_see_doctor": [
        "๐จ ุงูุฃูู ูุณุชูุฑ ุฃูุชุฑ ูู ุฃุณุจูุนูู",
        "๐ฆพ ุถุนู ุดุฏูุฏ ูู ุงููุชู",
        "๐ ูุด ูุงุฏุฑ ุชุฑูุน ุฅูุฏู ุฎุงูุต",
        "๐ ุงูุฃูู ุจูุตุญูู ูู ุงูููู",
        "๐ ุงููุณููุงุช ูุด ุจุชุฃุซุฑ"
      ],
      "recovery_plan": [
        "๐งโโ๏ธ ุชูุงุฑูู ุฅุทุงูุฉ ุงููุชู ุจุฑูู",
        "๐ช ุชูููุฉ ุงูุนุถูุงุช ุงูุฎูููุฉ ูููุชู",
        "๐ฏ ุชูุงุฑูู ุงููุฏู ุงูุญุฑูู",
        "๐๏ธโโ๏ธ ุงุฑุฌุน ููุฃูุฒุงู ุชุฏุฑูุฌูุงู",
        "โ๏ธ ุฑูุฒ ุนูู ุงูุชูุงุฒู ุงูุนุถูู"
      ],
      "prevention": [
        "๐ฅ ุณุฎู ุงููุชู ูููุณ ูุจู ุงูุชูุฑูู",
        "๐ช ููู ุงูุนุถูุงุช ุงูุฎูููุฉ ูููุชู",
        "๐ ุญุงูุธ ุนูู ูุถุนูุฉ ุตุญูุญุฉ",
        "โ๏ธ ูุงุฒู ุจูู ุชูุงุฑูู ุงูุฏูุน ูุงูุณุญุจ",
        "๐งโโ๏ธ ุงุนูู ุฅุทุงูุฉ ููุชุธูุฉ"
      ]
    },

    {
      "name_arabic": "ุชูุฒู ุงูุนุถูุฉ ุงูุฎูููุฉ",
      "name_english": "Hamstring Tear",
      "emoji": "๐ฆต",
      "affected_area": "ุงูุนุถูุฉ ุงูุฎูููุฉ ูููุฎุฐ (ุงููุงูุณุชุฑููุฌ)",
      "causes": [
        "ุฌุฑู ุณุฑูุน ุจุฏูู ุฅุญูุงุก ูุงูู ๐โโ๏ธ",
        "ุชูุงุฑูู ููุฒ ููุงุฌุฆุฉ",
        "ุนุฏู ุชูุงุฒู ุจูู ุงูุนุถูุฉ ุงูุฃูุงููุฉ ูุงูุฎูููุฉ",
        "ุฅุทุงูุฉ ููุฑุทุฉ ุฃู ุญุฑูุฉ ููุงุฌุฆุฉ",
        "ุฅุฑูุงู ุงูุนุถูุฉ ุฃู ุถุนููุง"
      ],
      "symptoms": [
        "ุฃูู ุญุงุฏ ููุงุฌุฆ ูู ุฎูู ุงููุฎุฐ ๐ฑ",
        "ุตูุช 'ุทูุฉ' ูุญุธุฉ ุงูุฅุตุงุจุฉ",
        "ุตุนูุจุฉ ูู ุงููุดู ุฃู ุงูุฌุฑู",
        "ุฃูู ููุง ุชูุฏ ุงูุฑุฌู ุฃู ุชุซูููุง",
        "ุฃุญูุงูุงู ูุฏูุฉ ุฃู ุชูุฑู"
      ],
      "first_aid": [
        "๐ ููู ุงููุดุงุท ููุฑุงู",
        "๐ง ุชูุฌ ููุฑุงู ููุฏุฉ 20 ุฏูููุฉ",
        "๐ฆต ุงุฑูุน ุงูุฑุฌู ุงููุตุงุจุฉ",
        "๐ฉน ุงุฑุจุท ุงูููุทูุฉ ุจุฑุจุงุท ุถุงุบุท ุฎููู",
        "๐ซ ูุชุญุงููุด ุชูุดู ุฃู ุชุฌุฑู"
      ],
      "when_to_see_doctor": [
        "๐จ ุฃูู ุดุฏูุฏ ุฌุฏุงู ููุด ูุงุฏุฑ ุชูุดู",
        "๐ ุชูุฑู ูุจูุฑ ุฃู ูุฏูุฉ ุดุฏูุฏุฉ",
        "โฐ ุงูุฃูู ูุด ุจูุชุญุณู ุจุนุฏ 3 ุฃูุงู",
        "๐ฆต ูุด ูุงุฏุฑ ุชุญุฑู ุงูุฑุฌู ุฎุงูุต",
        "๐ ุณูุนุช ุตูุช 'ุทูุฉ' ูุงุถุญ ููุช ุงูุฅุตุงุจุฉ"
      ],
      "recovery_plan": [
        "๐ถโโ๏ธ ูุดู ุฎููู ุจุนุฏ ูุง ุงูุฃูู ููุฏุฃ",
        "๐งโโ๏ธ ุฅุทุงูุฉ ุชุฏุฑูุฌูุฉ ููุนุถูุฉ",
        "๐ช ุชูููุฉ ุงูุนุถูุฉ ุจุฑูู",
        "๐โโ๏ธ ุชูุงุฑูู ูุงุฆูุฉ",
        "๐โโ๏ธ ุงุฑุฌุน ููุฌุฑู ุชุฏุฑูุฌูุงู"
      ],
      "prevention": [
        "๐ฅ ุฅุญูุงุก ุดุงูู ูุจู ุฃู ูุดุงุท ุณุฑูุน",
        "๐งโโ๏ธ ุฅุทุงูุฉ ููุชุธูุฉ ููุนุถูุฉ ุงูุฎูููุฉ",
        "๐ช ููู ุงูุนุถูุฉ ุงูุฎูููุฉ ูุงูุฃูุงููุฉ ุจุชูุงุฒู",
        "โ๏ธ ุชุฌูุจ ุงูุฒูุงุฏุฉ ุงูููุงุฌุฆุฉ ูู ุงูุดุฏุฉ",
        "๐ด ุฑุงุญุฉ ูุงููุฉ ุจูู ุงูุชูุงุฑูู"
      ]
    },

    {
      "name_arabic": "ุงูุชูุงุก ุงููุงุญู",
      "name_english": "Ankle Sprain",
      "emoji": "๐ฆถ",
      "affected_area": "ุงููุงุญู (ุงูุฃุฑุจุทุฉ ุญูุงููู ุงูููุตู)",
      "causes": [
        "ูุจูุท ุบูุท ุจุนุฏ ุงูููุฒ ๐ฆ",
        "ุงููุดู ุนูู ุณุทุญ ุบูุฑ ูุณุชูู",
        "ุชุบููุฑ ุงุชุฌุงู ููุงุฌุฆ ุฃุซูุงุก ุงูุฌุฑู",
        "ุถุนู ุนุถูุงุช ุงููุงุญู",
        "ูุจุณ ุญุฐุงุก ุบูุฑ ููุงุณุจ"
      ],
      "symptoms": [
        "ุฃูู ููุฑู ูู ุงููุงุญู ๐",
        "ุชูุฑู ุญูู ุงูููุตู",
        "ุตุนูุจุฉ ูู ุงููุดู ุฃู ุงููููู",
        "ูุฏูุฉ ุฃู ุชุบูุฑ ููู ุงูุฌูุฏ",
        "ุนุฏู ุซุจุงุช ูู ุงููุงุญู"
      ],
      "first_aid": [
        "๐ ููู ุงููุดู ููุฑุงู",
        "๐ง ุชูุฌ ููุฏุฉ 20 ุฏูููุฉ ูู ุณุงุนุชูู",
        "๐ฉน ุงุฑุจุท ุงููุงุญู ุจุฑุจุงุท ูุฑู",
        "๐ฆถ ุงุฑูุน ุงููุฏู ููู ูุณุชูู ุงูููุจ",
        "๐ซ ูุชุญุทุด ูุฒู ุนูู ุงููุฏู ุงููุตุงุจุฉ"
      ],
      "when_to_see_doctor": [
        "๐จ ุฃูู ุดุฏูุฏ ููุด ูุงุฏุฑ ุชุญุท ูุฒู ุนูู ุงููุฏู",
        "๐ ุชูุฑู ุดุฏูุฏ ุฃู ุชุดูู ูู ุงููุงุญู",
        "๐ข ุชูููู ุฃู ููุฏุงู ุงูุฅุญุณุงุณ",
        "โฐ ูุด ุจูุชุญุณู ุจุนุฏ 2-3 ุฃูุงู",
        "๐ ุงูุชูุงุก ูุชูุฑุฑ ูู ููุณ ุงููุงุญู"
      ],
      "recovery_plan": [
        "๐ถโโ๏ธ ูุดู ุชุฏุฑูุฌู ุจุนุฏ ุชุญุณู ุงูุฃูู",
        "๐งโโ๏ธ ุชูุงุฑูู ูุฏู ุญุฑูู ูููุงุญู",
        "๐ช ุชูููุฉ ุนุถูุงุช ุงููุงุญู ูุงูุณูุงูุฉ",
        "โ๏ธ ุชูุงุฑูู ุชูุงุฒู ูุซุจุงุช",
        "๐โโ๏ธ ุงุฑุฌุน ููุฃูุดุทุฉ ุชุฏุฑูุฌูุงู"
      ],
      "prevention": [
        "๐ฅ ุณุฎู ุงููุงุญู ูุจู ุงูุชูุฑูู",
        "๐ ุงูุจุณ ุญุฐุงุก ุฑูุงุถู ููุงุณุจ ููุฑุจูุท ูููุณ",
        "๐ช ููู ุนุถูุงุช ุงููุงุญู ูุงูุณูุงูุฉ",
        "โ๏ธ ุชูุงุฑูู ุชูุงุฒู ููุชุธูุฉ",
        "๐ ุฎูู ุจุงูู ูู ุงูุฃุฑุถ ุงููู ุจุชูุดู ุนูููุง"
      ]
    },

    {
      "name_arabic": "ุฃูู ุงููุนุตู",
      "name_english": "Wrist Pain/Sprain",
      "emoji": "โ",
      "affected_area": "ุงููุนุตู ูุงูุฃุฑุจุทุฉ ุงููุญูุทุฉ",
      "causes": [
        "ุญูู ุฃูุฒุงู ุชูููุฉ ุจูุจุถุฉ ุบูุท โ",
        "ุชูุงุฑูู ุจูุด ุฃุจ ุจูุถุนูุฉ ุฎุงุทุฆุฉ",
        "ุงุณุชุฎุฏุงู ููุฑุท ูููุงุชู ุฃู ุงูููุจููุชุฑ",
        "ุณููุท ุนูู ุงููุฏ ุงูููุฏูุฏุฉ",
        "ุญุฑูุงุช ูุชูุฑุฑุฉ ูููุนุตู"
      ],
      "symptoms": [
        "ุฃูู ูู ุงููุนุตู ุฎุงุตุฉ ูุน ุงูุญุฑูุฉ ๐ฃ",
        "ุชูุจุณ ุฃู ุตุนูุจุฉ ูู ุชุญุฑูู ุงููุนุตู",
        "ุฃูู ุจูุฒูุฏ ูุน ุงูุฅูุณุงู ุจุงูุฃุดูุงุก",
        "ุฃุญูุงูุงู ุชูุฑู ุฃู ุงูุชูุงุฎ",
        "ุถุนู ูู ููุฉ ุงููุจุถุฉ"
      ],
      "first_aid": [
        "๐ ููู ุฃู ูุดุงุท ูุณุจุจ ุฃูู",
        "๐ง ุชูุฌ ููุฏุฉ 15 ุฏูููุฉ ุนุฏุฉ ูุฑุงุช",
        "๐ฉน ุงุฑุจุท ุงููุนุตู ุจุฑุจุงุท ุฏุงุนู",
        "โ ุงุฑูุน ุงููุฏ ููู ูุณุชูู ุงูููุจ",
        "๐ ูุณูู ุจุณูุท ูู ุงูุฃูู ุดุฏูุฏ"
      ],
      "when_to_see_doctor": [
        "๐จ ุฃูู ุดุฏูุฏ ุฃู ุชุดูู ูุงุถุญ",
        "๐ข ุชูููู ุฃู ููุฏุงู ุงูุฅุญุณุงุณ ูู ุงูุฃุตุงุจุน",
        "๐ ุชูุฑู ุดุฏูุฏ ุฃู ุชุบูุฑ ููู",
        "โ ูุด ูุงุฏุฑ ุชุญุฑู ุงููุนุตู ุฃู ุงูุฃุตุงุจุน",
        "โฐ ุงูุฃูู ูุณุชูุฑ ุฃูุชุฑ ูู ุฃุณุจูุน"
      ],
      "recovery_plan": [
        "๐งโโ๏ธ ุชูุงุฑูู ุฅุทุงูุฉ ุฎูููุฉ ูููุนุตู",
        "๐ช ุชูููุฉ ุนุถูุงุช ุงูุณุงุนุฏ ุชุฏุฑูุฌูุงู",
        "๐ฏ ุชูุงุฑูู ูุฏู ุญุฑูู",
        "๐๏ธโโ๏ธ ุงุฑุฌุน ููุฃูุฒุงู ุจุญุฐุฑ",
        "โ๏ธ ุงุณุชุฎุฏู ุฏุนุงูุฉ ุงููุนุตู ูู ูุฒู"
      ],
      "prevention": [
        "๐ฅ ุณุฎู ุงููุนุตู ูุจู ุงูุชูุฑูู",
        "๐ ุญุงูุธ ุนูู ูุถุนูุฉ ุตุญูุญุฉ ูููุนุตู",
        "โ๏ธ ุงุณุชุฎุฏู ุฃูุฒุงู ููุงุณุจุฉ ูููุชู",
        "๐งโโ๏ธ ุงุนูู ุฅุทุงูุฉ ูููุนุตู ูุงูุณุงุนุฏ",
        "โฐ ุฎุฐ ูุชุฑุงุช ุฑุงุญุฉ ูู ุงูุฃูุดุทุฉ ุงููุชูุฑุฑุฉ"
      ]
    }
  ],

  "emergency_signs": {
    "title": "ุนูุงูุงุช ุงูุฎุทุฑ - ูุงุฒู ุชุฑูุญ ุงููุณุชุดูู ููุฑุงู! ๐จ",
    "signs": [
      "๐ฉธ ูุฒูู ุดุฏูุฏ ูุด ุจูููู",
      "๐ฆด ุดู ูู ูุณุฑ ุฃู ุฎูุน",
      "๐ง ููุฏุงู ุงููุนู ุฃู ุฏูุฎุฉ ุดุฏูุฏุฉ",
      "๐ ุฃูู ูู ุงูุตุฏุฑ ุฃู ุตุนูุจุฉ ูู ุงูุชููุณ",
      "๐คข ุบุซูุงู ุฃู ููุก ูุณุชูุฑ",
      "๐ก๏ธ ุญูู ุนุงููุฉ ูุน ุงูุฅุตุงุจุฉ"
    ]
  },

  "recovery_nutrition": {
    "title": "ุฃูู ูุณุงุนุฏ ุนูู ุงูุงุณุชุดูุงุก ๐",
    "foods": [
      "๐ ุณูู ุบูู ุจุงูุฃูููุบุง 3 (ุณููููุ ุชููุฉ)",
      "๐ฅฌ ุฎุถุฑูุงุช ูุฑููุฉ ุฎุถุฑุงุก",
      "๐ ููุงูู ุบููุฉ ุจููุชุงููู C",
      "๐ฅ ููุณุฑุงุช ูุจุฐูุฑ",
      "๐ ุจุฑูุชูู ุนุงูู ุงูุฌูุฏุฉ",
      "๐ง ุฃุทุนูุฉ ูุถุงุฏุฉ ููุงูุชูุงุจ (ุฒูุฌุจููุ ูุฑูู)"
    ]
  },

  "final_advice": {
    "title": "ูููุฉ ุฃุฎูุฑุฉ ูุง ุจุทู ๐ช",
    "message": "ุงูุฌูู ููุงู ุฑุงุฆุน ููุตุญุฉ ูุงูููุฉุ ุจุณ ุงูุฃูุงู ุฃูู ูู ุฃู ุญุงุฌุฉ ุชุงููุฉ. ูุชุณุชุนุฌูุด ุงููุชุงูุฌุ ูุฎูู ุจุงูู ูู ุฌุณูู. ูู ุญุณูุช ุจุฃู ุฃูู ุบุฑูุจุ ูุชุชุฌุงูููุด. ุงูููุงูุฉ ุฃุญุณู ูู ุงูุนูุงุฌุ ูุงูุตุจุฑ ููุชุงุญ ุงููุฌุงุญ! ๐ฅ"
  }
}